Metadata-Version: 2.1
Name: ubub
Version: 0.0.1.dev0
Summary: "A (micro)python library for pub-sub messaging for (u)asyncio apps"
Home-page: https://github.com/kumekay/ubub
Author: Sergei Silnov
Author-email: po@kumekay.com
License: UNKNOWN
Project-URL: Bug Tracker, https://github.com/kumekay/ubub/issues
Platform: UNKNOWN
Classifier: Framework :: AsyncIO
Classifier: Intended Audience :: Developers
Classifier: Programming Language :: Python :: 3
Classifier: Programming Language :: Python :: Implementation :: MicroPython
Classifier: License :: OSI Approved :: MIT License
Classifier: Operating System :: OS Independent
License-File: LICENSE
